Metadata-Version: 1.0
Name: pypicohp
Version: 0.1.3
Summary: Python binding for picohttpparser.
Home-page: UNKNOWN
Author: Sepehr Hamzehlouy
Author-email: s.hamzelooy@gmail.com
License: UNKNOWN
Platform: UNKNOWN
